cambridge/__init__.py
cambridge/args.py
cambridge/cache.py
cambridge/camb.py
cambridge/color.py
cambridge/console.py
cambridge/log.py
cambridge/main.py
cambridge/utils.py
cambridge/webster.py
cambridge-3.14.1.dist-info/entry_points.txt
cambridge-3.14.1.dist-info/licenses/LICENSE
cambridge-3.14.1.dist-info/WHEEL
cambridge-3.14.1.dist-info/METADATA
cambridge-3.14.1.dist-info/RECORD
