Metadata-Version: 2.4
Name: cambridge
Version: 3.14.1
Summary: cambridge is a terminal version of Cambridge Dictionary.
Home-page: https://github.com/KateWang2016/cambridge
Keywords: dictionary, cambridge, webster, English, web scraping, python
Author: Kate Wang
Author-email: kate.wang2018@gmail.com
Requires-Python: >=3.11
Classifier: License :: OSI Approved :: GNU General Public License v3 or later (GPLv3+)
Classifier: Programming Language :: Python :: 3
Classifier: Environment :: Console
License-File: LICENSE
Requires-Dist: aiohttp
Requires-Dist: beautifulsoup4
Requires-Dist: fake-user-agent
Requires-Dist: lxml
Requires-Dist: flit ; extra == "publish"
Provides-Extra: publish
